sctn/__init__.py
sctn/graphs.py
sctn/layers.py
sctn/numba_helper.py
sctn/resonator.py
sctn/spiking_encoders.py
sctn/spiking_network.py
sctn/spiking_neuron.py
sctn/learning_rules/__init__.py
sctn/learning_rules/learning_rule.py
sctn/learning_rules/stdp.py
sctn/learning_rules/supervised_stdp.py
sctn-0.1.4.dist-info/METADATA
sctn-0.1.4.dist-info/WHEEL
sctn-0.1.4.dist-info/dependency_links.txt
sctn-0.1.4.dist-info/top_level.txt
sctn-0.1.4.dist-info/RECORD
