Metadata-Version: 2.1
Name: sctn
Version: 0.1.4
Summary: Spiking Continues Time Neuron
Author: Yakir Hadad
Author-email: yakir4123@email.com>
Keywords: python,snn,ai
Classifier: Development Status :: 3 - Alpha
Classifier: Intended Audience :: Education
Classifier: Programming Language :: Python :: 3
Requires-Dist: numpy ~=1.26.2
Requires-Dist: numba ~=0.58.1
Requires-Dist: networkx ~=3.2.1
Requires-Dist: matplotlib ~=3.8.2
Requires-Dist: scipy ~=1.14.0
Requires-Dist: pandas ~=2.2.2
Requires-Dist: tqdm ~=4.66.4
Requires-Dist: torch ~=2.3.1
Requires-Dist: altair[all]
